reconnaissance/__init__.py
reconnaissance/recon.py
reconnaissance/WHOISsource/__init__.py
reconnaissance/WHOISsource/whois_source.py
reconnaissance/certificatesource/__init__.py
reconnaissance/certificatesource/certanalysis.py
reconnaissance/emailsources/__init__.py
reconnaissance/emailsources/emailformat.py
reconnaissance/emailsources/hunter.py
reconnaissance/emailsources/minelead.py
reconnaissance/emailsources/scraper.py
reconnaissance/scanners/__init__.py
reconnaissance/scanners/file_exposure_scanner.py
reconnaissance/scanners/xss_scanner.py
reconnaissance/subdomainsource/__init__.py
reconnaissance/subdomainsource/crtsh_source.py
reconnaissance/subdomainsource/subdomainenumeration.py
reconnaissance/threatintelsource/__init__.py
reconnaissance/threatintelsource/threatintel.py
reconnaissance/urlsource/__init__.py
reconnaissance/urlsource/graburls.py
tests/__init__.py
reconnaissance-1.0.3.dist-info/LICENSE
reconnaissance-1.0.3.dist-info/METADATA
reconnaissance-1.0.3.dist-info/WHEEL
reconnaissance-1.0.3.dist-info/top_level.txt
reconnaissance-1.0.3.dist-info/RECORD
